{"namedChunkGroups":{"polyfill":{"name":"polyfill","assets":[{"name":"polyfill.js","size":755828}],"filteredAssets":0,"assetsSize":755828,"filteredAuxiliaryAssets":0,"auxiliaryAssetsSize":0},"commons":{"name":"commons","assets":[{"name":"framework.js","size":2683904},{"name":"commons.css","size":10938},{"name":"commons.js","size":2711173}],"filteredAssets":0,"assetsSize":5406015,"filteredAuxiliaryAssets":0,"auxiliaryAssetsSize":0},"component---cache-dev-404-page-js":{"name":"component---cache-dev-404-page-js","assets":[{"name":"component---cache-dev-404-page-js.js","size":77616}],"filteredAssets":0,"assetsSize":77616,"filteredAuxiliaryAssets":0,"auxiliaryAssetsSize":0},"component---src-pages-404-js":{"name":"component---src-pages-404-js","assets":[{"name":"framework.js","size":2683904},{"name":"commons.css","size":10938},{"name":"commons.js","size":2711173},{"name":"component---src-pages-404-js.js","size":154684}],"filteredAssets":0,"assetsSize":5560699,"filteredAuxiliaryAssets":0,"auxiliaryAssetsSize":0},"component---src-pages-index-js":{"name":"component---src-pages-index-js","assets":[{"name":"framework.js","size":2683904},{"name":"commons.css","size":10938},{"name":"commons.js","size":2711173},{"name":"component---src-pages-index-js.js","size":159443}],"filteredAssets":0,"assetsSize":5565458,"filteredAuxiliaryAssets":0,"auxiliaryAssetsSize":0},"component---src-pages-page-2-js":{"name":"component---src-pages-page-2-js","assets":[{"name":"framework.js","size":2683904},{"name":"commons.css","size":10938},{"name":"commons.js","size":2711173},{"name":"component---src-pages-page-2-js.js","size":155203}],"filteredAssets":0,"assetsSize":5561218,"filteredAuxiliaryAssets":0,"auxiliaryAssetsSize":0},"component---src-pages-using-typescript-tsx":{"name":"component---src-pages-using-typescript-tsx","assets":[{"name":"framework.js","size":2683904},{"name":"commons.css","size":10938},{"name":"commons.js","size":2711173},{"name":"component---src-pages-using-typescript-tsx.js","size":159753}],"filteredAssets":0,"assetsSize":5565768,"filteredAuxiliaryAssets":0,"auxiliaryAssetsSize":0}},"assetsByChunkName":{"polyfill":["polyfill.js"],"commons":["framework.js","commons.css","commons.js"],"component---cache-dev-404-page-js":["component---cache-dev-404-page-js.js"],"component---src-pages-404-js":["framework.js","commons.css","commons.js","component---src-pages-404-js.js"],"component---src-pages-index-js":["framework.js","commons.css","commons.js","component---src-pages-index-js.js"],"component---src-pages-page-2-js":["framework.js","commons.css","commons.js","component---src-pages-page-2-js.js"],"component---src-pages-using-typescript-tsx":["framework.js","commons.css","commons.js","component---src-pages-using-typescript-tsx.js"]},"childAssetsByChunkName":{}}